narr/__init__.py
narr/_modidx.py
narr/atyp.py
narr/axes.py
narr/axis.py
narr/cons.py
narr/copy.py
narr/errs.py
narr/narr.py
narr/strs.py
narr-0.0.1.dist-info/LICENSE
narr-0.0.1.dist-info/METADATA
narr-0.0.1.dist-info/WHEEL
narr-0.0.1.dist-info/entry_points.txt
narr-0.0.1.dist-info/top_level.txt
narr-0.0.1.dist-info/RECORD
