Metadata-Version: 2.1
Name: narr
Version: 0.0.1
Summary: Literal Enum
Home-page: https://github.com/dsm-72/narr
Author: dsm-72
Author-email: sumner.magruder@yale.edu
License: Apache Software License 2.0
Keywords: named arrays narr nymstr fuzstr synset ispec xarray xarr xarray-like numpy np
Classifier: Development Status :: 4 - Beta
Classifier: Intended Audience :: Developers
Classifier: Natural Language :: English
Classifier: Programming Language :: Python :: 3.11
Classifier: License :: OSI Approved :: Apache Software License
Requires-Python: >=3.11
License-File: LICENSE
Requires-Dist: atyp
Requires-Dist: regsyn
Requires-Dist: indoc
Requires-Dist: ispec
Requires-Dist: pstr
Requires-Dist: aspec
Requires-Dist: fuzstr
Requires-Dist: nymstr
Requires-Dist: synset
Provides-Extra: dev
